dawn_python-0.3.0.dist-info/licenses/LICENSE
pydawn/__init__.py
pydawn/utils.py
pydawn/webgpu.py
pydawn/lib/libwebgpu_dawn.dll
pydawn/lib/libwebgpu_dawn_aarch64.so
pydawn/lib/libwebgpu_dawn_arm64.dylib
pydawn/lib/libwebgpu_dawn_x86_64.dylib
pydawn/lib/libwebgpu_dawn_x86_64.so
dawn_python-0.3.0.dist-info/METADATA
dawn_python-0.3.0.dist-info/WHEEL
dawn_python-0.3.0.dist-info/top_level.txt
dawn_python-0.3.0.dist-info/RECORD
