Metadata-Version: 2.4
Name: dawn-python
Version: 0.3.0
Summary: A Python interface for the Dawn WebGPU engine.
Home-page: https://github.com/wpmed92/pydawn
Author: Ahmed Harmouche
Author-email: ahmedharmouche92@gmail.com
Platform: macOS
Classifier: Programming Language :: Python :: 3
Classifier: Operating System :: MacOS
Classifier: Operating System :: POSIX :: Linux
Classifier: License :: OSI Approved :: BSD License
Requires-Python: >=3.7
License-File: LICENSE
Dynamic: author
Dynamic: author-email
Dynamic: classifier
Dynamic: description
Dynamic: description-content-type
Dynamic: home-page
Dynamic: license-file
Dynamic: platform
Dynamic: requires-python
Dynamic: summary
